Workbook
Name in_revenue_2026_01: Inputs!$B$2
Name in_revenue_2026_02: Inputs!$C$2
Name in_revenue_2026_03: Inputs!$D$2
Name in_revenue_2026_04: Inputs!$E$2
Name in_cogs_2026_01: Inputs!$B$3
Name in_cogs_2026_02: Inputs!$C$3
Name in_cogs_2026_03: Inputs!$D$3
Name in_cogs_2026_04: Inputs!$E$3
Name in_sganda_2026_01: Inputs!$B$4
Name in_sganda_2026_02: Inputs!$C$4
Name in_sganda_2026_03: Inputs!$D$4
Name in_sganda_2026_04: Inputs!$E$4
Name in_randd_2026_01: Inputs!$B$5
Name in_randd_2026_02: Inputs!$C$5
Name in_randd_2026_03: Inputs!$D$5
Name in_randd_2026_04: Inputs!$E$5
Name in_depreciation_2026_01: Inputs!$B$6
Name in_depreciation_2026_02: Inputs!$C$6
Name in_depreciation_2026_03: Inputs!$D$6
Name in_depreciation_2026_04: Inputs!$E$6
Name in_interest_expense_2026_01: Inputs!$B$7
Name in_interest_expense_2026_02: Inputs!$C$7
Name in_interest_expense_2026_03: Inputs!$D$7
Name in_interest_expense_2026_04: Inputs!$E$7
Name in_interest_income_2026_01: Inputs!$B$8
Name in_interest_income_2026_02: Inputs!$C$8
Name in_interest_income_2026_03: Inputs!$D$8
Name in_interest_income_2026_04: Inputs!$E$8
Name in_tax_expense_2026_01: Inputs!$B$9
Name in_tax_expense_2026_02: Inputs!$C$9
Name in_tax_expense_2026_03: Inputs!$D$9
Name in_tax_expense_2026_04: Inputs!$E$9
Name in_cash_2026_01: Inputs!$B$10
Name in_cash_2026_02: Inputs!$C$10
Name in_cash_2026_03: Inputs!$D$10
Name in_cash_2026_04: Inputs!$E$10
Name in_ar_2026_01: Inputs!$B$11
Name in_ar_2026_02: Inputs!$C$11
Name in_ar_2026_03: Inputs!$D$11
Name in_ar_2026_04: Inputs!$E$11
Name in_inventory_2026_01: Inputs!$B$12
Name in_inventory_2026_02: Inputs!$C$12
Name in_inventory_2026_03: Inputs!$D$12
Name in_inventory_2026_04: Inputs!$E$12
Name in_prepaid_expenses_2026_01: Inputs!$B$13
Name in_prepaid_expenses_2026_02: Inputs!$C$13
Name in_prepaid_expenses_2026_03: Inputs!$D$13
Name in_prepaid_expenses_2026_04: Inputs!$E$13
Name in_ppe_2026_01: Inputs!$B$14
Name in_ppe_2026_02: Inputs!$C$14
Name in_ppe_2026_03: Inputs!$D$14
Name in_ppe_2026_04: Inputs!$E$14
Name in_intangibles_2026_01: Inputs!$B$15
Name in_intangibles_2026_02: Inputs!$C$15
Name in_intangibles_2026_03: Inputs!$D$15
Name in_intangibles_2026_04: Inputs!$E$15
Name in_ap_2026_01: Inputs!$B$16
Name in_ap_2026_02: Inputs!$C$16
Name in_ap_2026_03: Inputs!$D$16
Name in_ap_2026_04: Inputs!$E$16

Sheet Inputs
A1: Model line | B1: 2026-01 | C1: 2026-02 | D1: 2026-03 | E1: 2026-04
A2: Revenue | B2: 2567482.9 | C2: 2690522.5 | D2: 2734888.8
A3: COGS | B3: -1455814.7 | C3: -1482369.1 | D3: -1506936.1
A4: SG&A | B4: -537326.51 | C4: -543642.53 | D4: -556144.4
A5: R&D | B5: -186696.7 | C5: -192269.04 | D5: -196346.72
A6: Depreciation | B6: -61192.92 | C6: -60823.67 | D6: -61592.78
A7: Interest expense | B7: -18188.45 | C7: -18576.47 | D7: -19352.6
A8: Interest income | B8: 4535.76 | C8: 4650.03 | D8: 4729.44
A9: Tax expense | B9: -77635.71 | C9: -78206.54 | D9: -79370.9
A10: Cash | B10: 4061311.9 | C10: 4035713.6 | D10: 4042830.8
A11: AR | B11: 1535361 | C11: 1535896.5 | D11: 1559808.2
A12: Inventory | B12: 1785211.8 | C12: 1803128.4 | D12: 1888324.8
A13: Prepaid expenses | B13: 118968.27 | C13: 120175.97 | D13: 124102.85
... A22: Retained earnings prior | B22: 6447689.2 | C22: 6271867.3 | D22: 6232248.5

Sheet IS
A1: Income Statement
B2: 2026-01 | C2: 2026-02 | D2: 2026-03 | E2: 2026-04
A3: Revenue | B3: =in_revenue_2026_01 | C3: =in_revenue_2026_02 | D3: =in_revenue_2026_03 | E3: =in_revenue_2026_04
A4: COGS | B4: =in_cogs_2026_01 | C4: =in_cogs_2026_02 | D4: =in_cogs_2026_03 | E4: =in_cogs_2026_04
A5: Gross profit | B5: =in_revenue_2026_01+in_cogs_2026_01 | C5: =in_revenue_2026_02+in_cogs_2026_02 | D5: =in_revenue_2026_03+in_cogs_2026_03 | E5: =in_revenue_2026_04+in_cogs_2026_04
A6: SG&A | B6: =in_sganda_2026_01 | C6: =in_sganda_2026_02 | D6: =in_sganda_2026_03 | E6: =in_sganda_2026_04
A7: R&D | B7: =in_randd_2026_01 | C7: =in_randd_2026_02 | D7: =in_randd_2026_03 | E7: =in_randd_2026_04
A8: Depreciation | B8: =in_depreciation_2026_01 | C8: =in_depreciation_2026_02 | D8: =in_depreciation_2026_03 | E8: =in_depreciation_2026_04
A9: Operating income | B9: =in_revenue_2026_01+in_cogs_2026_01+in_sganda_2026_01+in_randd_2026_01+in_depreciation_2026_01 | C9: =in_revenue_2026_02+in_cogs_2026_02+in_sganda_2026_02+in_randd_2026_02+in_depreciation_2026_02 | D9: =in_revenue_2026_03+in_cogs_2026_03+in_sganda_2026_03+in_randd_2026_03+in_depreciation_2026_03 | E9: =in_revenue_2026_04+in_cogs_2026_04+in_sganda_2026_04+in_randd_2026_04+in_depreciation_2026_04
A10: Interest income | B10: =in_interest_income_2026_01 | C10: =in_interest_income_2026_02 | D10: =in_interest_income_2026_03 | E10: =in_interest_income_2026_04
A11: Interest expense | B11: =in_interest_expense_2026_01 | C11: =in_interest_expense_2026_02 | D11: =in_interest_expense_2026_03 | E11: =in_interest_expense_2026_04
A12: Pretax income | B12: =in_revenue_2026_01+in_cogs_2026_01+in_sganda_2026_01+in_randd_2026_01+in_depreciation_2026_01+in_interest_income_2026_01+in_interest_expense_2026_01 | C12: =in_revenue_2026_02+in_cogs_2026_02+in_sganda_2026_02+in_randd_2026_02+in_depreciation_2026_02+in_interest_income_2026_02+in_interest_expense_2026_02 | D12: =in_revenue_2026_03+in_cogs_2026_03+in_sganda_2026_03+in_randd_2026_03+in_depreciation_2026_03+in_interest_income_2026_03+in_interest_expense_2026_03 | E12: =in_revenue_2026_04+in_cogs_2026_04+in_sganda_2026_04+in_randd_2026_04+in_depreciation_2026_04+in_interest_income_2026_04+in_interest_expense_2026_04
A13: Tax expense | B13: =in_tax_expense_2026_01 | C13: =in_tax_expense_2026_02 | D13: =in_tax_expense_2026_03 | E13: =in_tax_expense_2026_04
A14: Net income | B14: =in_revenue_2026_01+in_cogs_2026_01+in_sganda_2026_01+in_randd_2026_01+in_depreciation_2026_01+in_interest_income_2026_01+in_interest_expense_2026_01+in_tax_expense_2026_01 | C14: =in_revenue_2026_02+in_cogs_2026_02+in_sganda_2026_02+in_randd_2026_02+in_depreciation_2026_02+in_interest_income_2026_02+in_interest_expense_2026_02+in_tax_expense_2026_02 | D14: =in_revenue_2026_03+in_cogs_2026_03+in_sganda_2026_03+in_randd_2026_03+in_depreciation_2026_03+in_interest_income_2026_03+in_interest_expense_2026_03+in_tax_expense_2026_03 | E14: =in_revenue_2026_04+in_cogs_2026_04+in_sganda_2026_04+in_randd_2026_04+in_depreciation_2026_04+in_interest_income_2026_04+in_interest_expense_2026_04+in_tax_expense_2026_04

Sheet BS
A1: Balance Sheet
B2: 2026-01 | C2: 2026-02 | D2: 2026-03 | E2: 2026-04
A3: Cash | B3: =in_cash_2026_01 | C3: =in_cash_2026_02 | D3: =in_cash_2026_03 | E3: =in_cash_2026_04
A4: AR | B4: =in_ar_2026_01 | C4: =in_ar_2026_02 | D4: =in_ar_2026_03 | E4: =in_ar_2026_04
A5: Inventory | B5: =in_inventory_2026_01 | C5: =in_inventory_2026_02 | D5: =in_inventory_2026_03 | E5: =in_inventory_2026_04
A6: Prepaid expenses | B6: =in_prepaid_expenses_2026_01 | C6: =in_prepaid_expenses_2026_02 | D6: =in_prepaid_expenses_2026_03 | E6: =in_prepaid_expenses_2026_04
A7: PPE (net) | B7: =in_ppe_2026_01 | C7: =in_ppe_2026_02 | D7: =in_ppe_2026_03 | E7: =in_ppe_2026_04
A8: Intangibles | B8: =in_intangibles_2026_01 | C8: =in_intangibles_2026_02 | D8: =in_intangibles_2026_03 | E8: =in_intangibles_2026_04
A9: Total assets | B9: =in_cash_2026_01+in_ar_2026_01+in_inventory_2026_01+in_prepaid_expenses_2026_01+in_ppe_2026_01+in_intangibles_2026_01 | C9: =in_cash_2026_02+in_ar_2026_02+in_inventory_2026_02+in_prepaid_expenses_2026_02+in_ppe_2026_02+in_intangibles_2026_02 | D9: =in_cash_2026_03+in_ar_2026_03+in_inventory_2026_03+in_prepaid_expenses_2026_03+in_ppe_2026_03+in_intangibles_2026_03 | E9: =in_cash_2026_04+in_ar_2026_04+in_inventory_2026_04+in_prepaid_expenses_2026_04+in_ppe_2026_04+in_intangibles_2026_04
A10: AP | B10: =in_ap_2026_01 | C10: =in_ap_2026_02 | D10: =in_ap_2026_03 | E10: =in_ap_2026_04
A11: Accrued expenses | B11: =in_accrued_expenses_2026_01 | C11: =in_accrued_expenses_2026_02 | D11: =in_accrued_expenses_2026_03 | E11: =in_accrued_expenses_2026_04
A12: Lease liability ST | B12: =in_lease_liability_st_2026_01 | C12: =in_lease_liability_st_2026_02 | D12: =in_lease_liability_st_2026_03 | E12: =in_lease_liability_st_2026_04
A13: Lease liability LT | B13: =in_lease_liability_lt_2026_01 | C13: =in_lease_liability_lt_2026_02 | D13: =in_lease_liability_lt_2026_03 | E13: =in_lease_liability_lt_2026_04
A14: Debt | B14: =in_debt_2026_01 | C14: =in_debt_2026_02 | D14: =in_debt_2026_03 | E14: =in_debt_2026_04
A15: Total liabilities | B15: =in_ap_2026_01+in_accrued_expenses_2026_01+in_lease_liability_st_2026_01+in_lease_liability_lt_2026_01+in_debt_2026_01 | C15: =in_ap_2026_02+in_accrued_expenses_2026_02+in_lease_liability_st_2026_02+in_lease_liability_lt_2026_02+in_debt_2026_02 | D15: =in_ap_2026_03+in_accrued_expenses_2026_03+in_lease_liability_st_2026_03+in_lease_liability_lt_2026_03+in_debt_2026_03 | E15: =in_ap_2026_04+in_accrued_expenses_2026_04+in_lease_liability_st_2026_04+in_lease_liability_lt_2026_04+in_debt_2026_04
A16: Common stock | B16: =in_common_stock_2026_01 | C16: =in_common_stock_2026_02 | D16: =in_common_stock_2026_03 | E16: =in_common_stock_2026_04
A17: Retained earnings | B17: =in_retained_earnings_prior_2026_01+IS!B14 | C17: =in_retained_earnings_prior_2026_02+IS!C14 | D17: =in_retained_earnings_prior_2026_03+IS!D14 | E17: =in_retained_earnings_prior_2026_04+IS!E14
A18: Total equity | B18: =in_common_stock_2026_01+in_retained_earnings_prior_2026_01+IS!B14 | C18: =in_common_stock_2026_02+in_retained_earnings_prior_2026_02+IS!C14 | D18: =in_common_stock_2026_03+in_retained_earnings_prior_2026_03+IS!D14 | E18: =in_common_stock_2026_04+in_retained_earnings_prior_2026_04+IS!E14
A19: Check (A - L - E) | B19: =B9-B15-B18 | C19: =C9-C15-C18 | D19: =D9-D15-D18 | E19: =E9-E15-E18

Sheet CF
A1: Cash Flow
B2: 2026-01 | C2: 2026-02 | D2: 2026-03 | E2: 2026-04
A3: Net income | B3: =IS!B14 | C3: =IS!C14 | D3: =IS!D14 | E3: =IS!E14
A4: + Depreciation | B4: =-in_depreciation_2026_01 | C4: =-in_depreciation_2026_02 | D4: =-in_depreciation_2026_03 | E4: =-in_depreciation_2026_04
A5: - Change in AR | C5: =-(in_ar_2026_02-in_ar_2026_01) | D5: =-(in_ar_2026_03-in_ar_2026_02) | E5: =-(in_ar_2026_04-in_ar_2026_03)
A6: - Change in Inventory | C6: =-(in_inventory_2026_02-in_inventory_2026_01) | D6: =-(in_inventory_2026_03-in_inventory_2026_02) | E6: =-(in_inventory_2026_04-in_inventory_2026_03)
A7: + Change in AP | C7: =in_ap_2026_02-in_ap_2026_01 | D7: =in_ap_2026_03-in_ap_2026_02 | E7: =in_ap_2026_04-in_ap_2026_03
A8: + Change in Accrued | C8: =in_accrued_expenses_2026_02-in_accrued_expenses_2026_01 | D8: =in_accrued_expenses_2026_03-in_accrued_expenses_2026_02 | E8: =in_accrued_expenses_2026_04-in_accrued_expenses_2026_03
A9: Cash from operations | B9: =SUM(B3:B8) | C9: =SUM(C3:C8) | D9: =SUM(D3:D8) | E9: =SUM(E3:E8)
A10: - Change in PPE | C10: =-(in_ppe_2026_02-in_ppe_2026_01) | D10: =-(in_ppe_2026_03-in_ppe_2026_02) | E10: =-(in_ppe_2026_04-in_ppe_2026_03)
A11: Cash from investing | B11: =B10 | C11: =C10 | D11: =D10 | E11: =E10
A12: + Change in Debt | C12: =in_debt_2026_02-in_debt_2026_01 | D12: =in_debt_2026_03-in_debt_2026_02 | E12: =in_debt_2026_04-in_debt_2026_03
A13: + Change in Lease liabilities | C13: =(in_lease_liability_st_2026_02-in_lease_liability_st_2026_01)+(in_lease_liability_lt_2026_02-in_lease_liability_lt_2026_01) | D13: =(in_lease_liability_st_2026_03-in_lease_liability_st_2026_02)+(in_lease_liability_lt_2026_03-in_lease_liability_lt_2026_02) | E13: =(in_lease_liability_st_2026_04-in_lease_liability_st_2026_03)+(in_lease_liability_lt_2026_04-in_lease_liability_lt_2026_03)
A14: Cash from financing | B14: =SUM(B12:B13) | C14: =SUM(C12:C13) | D14: =SUM(D12:D13) | E14: =SUM(E12:E13)
A15: Net change in cash | B15: =B8+B10+B14 | C15: =C8+C10+C14 | D15: =D8+D10+D14 | E15: =E8+E10+E14
A16: Memo: Change in cash on BS | C16: =in_cash_2026_02-in_cash_2026_01 | D16: =in_cash_2026_03-in_cash_2026_02 | E16: =in_cash_2026_04-in_cash_2026_03

Sheet README
A1: Three-statement model - sample for vibecoding case
A3: The Inputs tab holds period numbers. Jan/Feb/Mar are frozen actuals
A4: from prior monthly updates; April is empty and gets populated by
A5: the automation script the analyst runs each month.
A7: Each cell on Inputs has a defined name like in_revenue_2026_04 so
A8: the script can write by name rather than by cell coordinate.
A10: IS / BS / CF tabs reference Inputs through those names. Do not
A11: type numbers directly into IS, BS, or CF.
A13: Each new month, extend Inputs with one more column to the right
A14: and add defined names for the new period before running the
A15: script. The script does the rest.
A17: Sign convention on Inputs:
... A21: adds it back as a positive number.
